sphinxnotes/lilypond/__init__.py
sphinxnotes/lilypond/jianpu.py
sphinxnotes/lilypond/lilypond.py
sphinxnotes/lilypond/meta.py
sphinxnotes/lilypond/midi.py
sphinxnotes/lilypond/py.typed
sphinxnotes/lilypond/static/__init__.py
sphinxnotes/lilypond/static/sphinxnotes-lilypond.css
sphinxnotes/lilypond/static/sphinxnotes-lilypond.js
sphinxnotes_lilypond-2.4.dist-info/licenses/LICENSE
sphinxnotes_lilypond-2.4.dist-info/METADATA
sphinxnotes_lilypond-2.4.dist-info/WHEEL
sphinxnotes_lilypond-2.4.dist-info/top_level.txt
sphinxnotes_lilypond-2.4.dist-info/RECORD
